{"SMH_2917": {"risk": 0}, "SMH_1126": {"risk": 0}, "SMH_6094": {"risk": 0}, "SMH_4080": {"risk": 1}, "SMH_4617": {"risk": 0}, "SMH_6121": {"risk": 0}, "SMH_3841": {"risk": 0}, "SMH_3279": {"risk": 1}, "SMH_2922": {"risk": 0}, "SMH_1278": {"risk": 0}, "SMH_5010": {"risk": 1}, "SMH_5135": {"risk": 0}, "SMH_3827": {"risk": 0}, "SMH_5400": {"risk": 0}, "SMH_779": {"risk": 0}, "SMH_617": {"risk": 0}, "SMH_2677": {"risk": 0}, "SMH_956": {"risk": 0}, "SMH_2279": {"risk": 1}, "SMH_3794": {"risk": 0}, "SMH_2253": {"risk": 0}, "SMH_5467": {"risk": 0}, "SMH_2240": {"risk": 0}, "SMH_6140": {"risk": 0}, "SMH_4531": {"risk": 0}, "SMH_5883": {"risk": 0}, "SMH_2467": {"risk": 0}, "SMH_4112": {"risk": 1}, "SMH_2224": {"risk": 0}, "SMH_4885": {"risk": 1}, "SMH_5689": {"risk": 0}, "SMH_6163": {"risk": 0}, "SMH_4957": {"risk": 0}, "SMH_4076": {"risk": 0}, "SMH_5906": {"risk": 1}, "SMH_3183": {"risk": 0}, "SMH_2633": {"risk": 0}, "SMH_4634": {"risk": 0}, "SMH_6150": {"risk": 1}, "SMH_5698": {"risk": 1}, "SMH_4800": {"risk": 0}, "SMH_4666": {"risk": 0}, "SMH_4425": {"risk": 0}, "SMH_782": {"risk": 0}, "SMH_1895": {"risk": 0}, "SMH_2908": {"risk": 1}, "SMH_2914": {"risk": 1}, "SMH_3610": {"risk": 1}, "SMH_3397": {"risk": 0}, "SMH_2894": {"risk": 0}, "SMH_4086": {"risk": 1}, "SMH_4625": {"risk": 1}, "SMH_4695": {"risk": 0}, "SMH_1265": {"risk": 0}, "SMH_5996": {"risk": 0}, "SMH_1441": {"risk": 1}, "SMH_5546": {"risk": 0}, "SMH_5905": {"risk": 1}, "SMH_4915": {"risk": 0}, "SMH_3600": {"risk": 0}, "SMH_4985": {"risk": 0}, "SMH_5081": {"risk": 0}, "SMH_4850": {"risk": 0}, "SMH_4814": {"risk": 0}, "SMH_5891": {"risk": 0}, "SMH_5429": {"risk": 0}, "SMH_4104": {"risk": 1}, "SMH_4457": {"risk": 0}, "SMH_1042": {"risk": 0}, "SMH_5511": {"risk": 0}, "SMH_4869": {"risk": 0}, "SMH_2932": {"risk": 0}, "SMH_4941": {"risk": 0}, "SMH_2933": {"risk": 0}, "SMH_3918": {"risk": 1}, "SMH_5450": {"risk": 1}, "SMH_5274": {"risk": 0}, "SMH_5505": {"risk": 1}, "SMH_5417": {"risk": 0}, "SMH_808": {"risk": 1}, "SMH_934": {"risk": 0}, "SMH_4986": {"risk": 0}, "SMH_4058": {"risk": 0}, "SMH_624": {"risk": 0}, "SMH_4916": {"risk": 0}, "SMH_3750": {"risk": 1}, "SMH_1144": {"risk": 0}, "SMH_4400": {"risk": 0}, "SMH_5094": {"risk": 0}, "SMH_3804": {"risk": 1}, "SMH_5625": {"risk": 0}, "SMH_5151": {"risk": 1}, "SMH_1011": {"risk": 1}, "SMH_2241": {"risk": 0}, "SMH_2970": {"risk": 1}, "SMH_4200": {"risk": 1}, "SMH_5952": {"risk": 0}, "SMH_1849": {"risk": 0}, "SMH_5953": {"risk": 0}, "SMH_947": {"risk": 0}, "SMH_2597": {"risk": 0}, "SMH_4593": {"risk": 1}, "SMH_5238": {"risk": 1}, "SMH_2899": {"risk": 1}, "SMH_3012": {"risk": 0}, "SMH_3396": {"risk": 0}, "SMH_890": {"risk": 0}, "SMH_5498": {"risk": 0}, "SMH_4098": {"risk": 0}, "SMH_3519": {"risk": 0}, "SMH_1673": {"risk": 0}, "SMH_2312": {"risk": 0}, "SMH_1953": {"risk": 1}, "SMH_1245": {"risk": 1}, "SMH_999": {"risk": 0}, "SMH_1528": {"risk": 0}, "SMH_5320": {"risk": 1}, "SMH_5433": {"risk": 0}, "SMH_4586": {"risk": 0}, "SMH_2828": {"risk": 1}, "SMH_4789": {"risk": 1}, "SMH_5384": {"risk": 0}, "SMH_4572": {"risk": 0}, "SMH_4085": {"risk": 1}, "SMH_5669": {"risk": 0}, "SMH_5272": {"risk": 0}, "SMH_1375": {"risk": 0}, "SMH_4063": {"risk": 0}, "SMH_2742": {"risk": 0}, "SMH_4867": {"risk": 1}, "SMH_4705": {"risk": 1}, "SMH_1254": {"risk": 0}, "SMH_3963": {"risk": 0}, "SMH_4077": {"risk": 0}, "SMH_3893": {"risk": 0}, "SMH_5877": {"risk": 0}, "SMH_5194": {"risk": 0}, "SMH_2285": {"risk": 1}, "SMH_1207": {"risk": 1}, "SMH_2641": {"risk": 1}, "SMH_5846": {"risk": 1}, "SMH_6109": {"risk": 1}, "SMH_5111": {"risk": 1}, "SMH_5039": {"risk": 1}, "SMH_4737": {"risk": 1}, "SMH_4064": {"risk": 0}, "SMH_2239": {"risk": 0}, "SMH_5201": {"risk": 1}, "SMH_4031": {"risk": 0}, "SMH_3740": {"risk": 0}, "SMH_3761": {"risk": 1}, "SMH_2576": {"risk": 0}, "SMH_2439": {"risk": 0}, "SMH_1488": {"risk": 0}, "SMH_6032": {"risk": 0}, "SMH_1302": {"risk": 0}, "SMH_3384": {"risk": 0}, "SMH_6116": {"risk": 0}, "SMH_4778": {"risk": 0}, "SMH_5501": {"risk": 1}, "SMH_3059": {"risk": 0}, "SMH_5908": {"risk": 0}, "SMH_1252": {"risk": 1}, "SMH_4092": {"risk": 0}, "SMH_5349": {"risk": 0}, "SMH_3529": {"risk": 0}, "SMH_1319": {"risk": 0}, "SMH_1099": {"risk": 1}, "SMH_4181": {"risk": 0}, "SMH_5518": {"risk": 0}, "SMH_1372": {"risk": 0}, "SMH_2880": {"risk": 0}, "SMH_4820": {"risk": 0}, "SMH_2527": {"risk": 1}, "SMH_4210": {"risk": 0}, "SMH_4021": {"risk": 0}, "SMH_1339": {"risk": 1}, "SMH_1815": {"risk": 0}, "SMH_5821": {"risk": 1}, "SMH_6034": {"risk": 0}, "SMH_3583": {"risk": 0}, "SMH_5798": {"risk": 0}, "SMH_5460": {"risk": 1}, "SMH_5592": {"risk": 0}, "SMH_5827": {"risk": 1}, "SMH_4329": {"risk": 0}, "SMH_5346": {"risk": 1}, "SMH_3235": {"risk": 0}, "SMH_2915": {"risk": 1}, "SMH_1547": {"risk": 0}, "SMH_795": {"risk": 0}, "SMH_3063": {"risk": 0}, "SMH_2884": {"risk": 0}, "SMH_2048": {"risk": 1}, "SMH_589": {"risk": 1}, "SMH_560": {"risk": 1}, "SMH_4075": {"risk": 0}, "SMH_4090": {"risk": 0}, "SMH_2244": {"risk": 0}, "SMH_5774": {"risk": 0}, "SMH_2238": {"risk": 0}, "SMH_5736": {"risk": 0}, "SMH_2456": {"risk": 0}, "SMH_5913": {"risk": 0}, "SMH_1226": {"risk": 0}, "SMH_584": {"risk": 0}, "SMH_3200": {"risk": 1}, "SMH_3527": {"risk": 0}, "SMH_2878": {"risk": 0}, "SMH_3274": {"risk": 0}, "SMH_2234": {"risk": 0}, "SMH_1260": {"risk": 0}, "SMH_4605": {"risk": 0}, "SMH_2350": {"risk": 0}, "SMH_2154": {"risk": 0}, "SMH_4052": {"risk": 1}, "SMH_2385": {"risk": 1}, "SMH_5126": {"risk": 0}, "SMH_1622": {"risk": 0}, "SMH_3701": {"risk": 0}, "SMH_2085": {"risk": 0}, "SMH_5642": {"risk": 1}, "SMH_6113": {"risk": 1}, "SMH_1299": {"risk": 0}, "SMH_5034": {"risk": 0}, "SMH_2236": {"risk": 1}, "SMH_5386": {"risk": 0}, "SMH_5405": {"risk": 0}, "SMH_5538": {"risk": 1}, "SMH_5209": {"risk": 0}, "SMH_5886": {"risk": 1}, "SMH_4802": {"risk": 0}, "SMH_5820": {"risk": 1}, "SMH_4034": {"risk": 1}, "SMH_761": {"risk": 1}, "SMH_4787": {"risk": 0}, "SMH_5462": {"risk": 0}, "SMH_5114": {"risk": 0}, "SMH_4452": {"risk": 0}, "SMH_5512": {"risk": 0}, "SMH_4993": {"risk": 1}, "SMH_5580": {"risk": 0}, "SMH_3537": {"risk": 0}, "SMH_3554": {"risk": 0}, "SMH_3487": {"risk": 0}, "SMH_5780": {"risk": 0}, "SMH_1508": {"risk": 0}, "SMH_3214": {"risk": 0}, "SMH_1103": {"risk": 0}, "SMH_5962": {"risk": 1}, "SMH_1250": {"risk": 0}, "SMH_2498": {"risk": 1}, "SMH_2889": {"risk": 0}, "SMH_4574": {"risk": 0}, "SMH_3511": {"risk": 0}, "SMH_5524": {"risk": 0}, "SMH_3559": {"risk": 0}, "SMH_1113": {"risk": 0}, "SMH_5157": {"risk": 1}, "SMH_5069": {"risk": 0}, "SMH_5330": {"risk": 1}, "SMH_4648": {"risk": 0}, "SMH_2258": {"risk": 1}, "SMH_5312": {"risk": 0}, "SMH_5195": {"risk": 1}, "SMH_572": {"risk": 0}, "SMH_2488": {"risk": 0}, "SMH_1686": {"risk": 0}, "SMH_3547": {"risk": 0}, "SMH_5670": {"risk": 0}, "SMH_2580": {"risk": 0}, "SMH_1699": {"risk": 0}, "SMH_4263": {"risk": 0}, "SMH_3820": {"risk": 0}, "SMH_2361": {"risk": 1}, "SMH_6023": {"risk": 0}, "SMH_2750": {"risk": 0}, "SMH_5976": {"risk": 0}, "SMH_1594": {"risk": 0}, "SMH_5587": {"risk": 0}, "SMH_4228": {"risk": 0}, "SMH_5451": {"risk": 0}, "SMH_5250": {"risk": 0}, "SMH_6020": {"risk": 0}, "SMH_3836": {"risk": 0}, "SMH_4406": {"risk": 1}, "SMH_4571": {"risk": 1}, "SMH_5489": {"risk": 0}, "SMH_2820": {"risk": 0}, "SMH_2300": {"risk": 1}, "SMH_4099": {"risk": 0}, "SMH_3594": {"risk": 0}, "SMH_4391": {"risk": 1}, "SMH_2838": {"risk": 1}, "SMH_4991": {"risk": 0}, "SMH_3813": {"risk": 1}, "SMH_5191": {"risk": 0}, "SMH_5352": {"risk": 1}, "SMH_2660": {"risk": 0}, "SMH_4042": {"risk": 0}, "SMH_5154": {"risk": 0}, "SMH_5695": {"risk": 0}, "SMH_5750": {"risk": 0}, "SMH_3056": {"risk": 0}, "SMH_5626": {"risk": 1}, "SMH_3440": {"risk": 1}, "SMH_2974": {"risk": 0}, "SMH_5673": {"risk": 1}, "SMH_1296": {"risk": 0}, "SMH_3448": {"risk": 0}, "SMH_792": {"risk": 0}, "SMH_4159": {"risk": 0}, "SMH_2228": {"risk": 0}, "SMH_1326": {"risk": 1}, "SMH_4158": {"risk": 1}, "SMH_5015": {"risk": 0}, "SMH_4989": {"risk": 0}, "SMH_3961": {"risk": 0}, "SMH_5561": {"risk": 0}, "SMH_1059": {"risk": 1}, "SMH_6122": {"risk": 1}, "SMH_4072": {"risk": 1}, "SMH_2790": {"risk": 1}, "SMH_1842": {"risk": 0}, "SMH_4548": {"risk": 0}, "SMH_5000": {"risk": 0}, "SMH_5706": {"risk": 0}, "SMH_4578": {"risk": 0}, "SMH_5617": {"risk": 0}, "SMH_5085": {"risk": 0}, "SMH_1768": {"risk": 1}, "SMH_6057": {"risk": 0}, "SMH_2267": {"risk": 1}, "SMH_4536": {"risk": 0}, "SMH_3920": {"risk": 0}, "SMH_5479": {"risk": 1}, "SMH_5988": {"risk": 0}, "SMH_4673": {"risk": 0}, "SMH_5369": {"risk": 1}, "SMH_3557": {"risk": 1}, "SMH_4573": {"risk": 1}, "SMH_4481": {"risk": 0}, "SMH_621": {"risk": 1}, "SMH_4044": {"risk": 0}, "SMH_5818": {"risk": 1}, "SMH_1070": {"risk": 0}, "SMH_3501": {"risk": 1}, "SMH_2627": {"risk": 0}, "SMH_2636": {"risk": 0}, "SMH_4663": {"risk": 0}, "SMH_5059": {"risk": 1}, "SMH_6019": {"risk": 0}, "SMH_5992": {"risk": 0}, "SMH_1311": {"risk": 0}, "SMH_3130": {"risk": 0}, "SMH_702": {"risk": 0}, "SMH_1210": {"risk": 0}, "SMH_5468": {"risk": 1}, "SMH_3872": {"risk": 0}, "SMH_5062": {"risk": 1}, "SMH_4632": {"risk": 1}, "SMH_4145": {"risk": 0}, "SMH_5893": {"risk": 1}, "SMH_5589": {"risk": 0}, "SMH_5335": {"risk": 1}, "SMH_1809": {"risk": 0}, "SMH_4948": {"risk": 0}, "SMH_3539": {"risk": 1}, "SMH_3919": {"risk": 0}, "SMH_5482": {"risk": 0}, "SMH_2696": {"risk": 0}, "SMH_5197": {"risk": 0}, "SMH_5347": {"risk": 1}, "SMH_5652": {"risk": 0}, "SMH_3071": {"risk": 0}, "SMH_5343": {"risk": 1}, "SMH_4132": {"risk": 0}, "SMH_2332": {"risk": 0}, "SMH_5926": {"risk": 0}, "SMH_2765": {"risk": 1}, "SMH_4187": {"risk": 0}, "SMH_6066": {"risk": 0}, "SMH_4954": {"risk": 0}, "SMH_5193": {"risk": 0}, "SMH_2255": {"risk": 0}, "SMH_5109": {"risk": 0}, "SMH_4988": {"risk": 1}, "SMH_3363": {"risk": 0}, "SMH_4185": {"risk": 0}, "SMH_1186": {"risk": 0}, "SMH_5696": {"risk": 0}, "SMH_1688": {"risk": 0}, "SMH_3144": {"risk": 0}, "SMH_2886": {"risk": 0}, "SMH_5084": {"risk": 0}, "SMH_5164": {"risk": 0}, "SMH_2773": {"risk": 1}, "SMH_3611": {"risk": 0}, "SMH_6189": {"risk": 0}, "SMH_5897": {"risk": 0}, "SMH_3598": {"risk": 0}, "SMH_5649": {"risk": 1}, "SMH_3937": {"risk": 0}, "SMH_3232": {"risk": 0}, "SMH_587": {"risk": 0}, "SMH_3508": {"risk": 0}, "SMH_1292": {"risk": 0}, "SMH_674": {"risk": 1}, "SMH_4962": {"risk": 0}, "SMH_698": {"risk": 0}, "SMH_6067": {"risk": 0}, "SMH_5975": {"risk": 0}, "SMH_1251": {"risk": 1}, "SMH_1745": {"risk": 0}, "SMH_4108": {"risk": 1}, "SMH_4036": {"risk": 1}, "SMH_4644": {"risk": 0}, "SMH_4111": {"risk": 1}, "SMH_4120": {"risk": 0}, "SMH_1887": {"risk": 1}, "SMH_3708": {"risk": 0}, "SMH_1288": {"risk": 0}, "SMH_810": {"risk": 0}, "SMH_2281": {"risk": 0}, "SMH_4642": {"risk": 0}, "SMH_1009": {"risk": 0}, "SMH_5253": {"risk": 0}, "SMH_3150": {"risk": 1}, "SMH_4975": {"risk": 0}, "SMH_2910": {"risk": 0}, "SMH_4088": {"risk": 0}, "SMH_3376": {"risk": 0}, "SMH_4761": {"risk": 1}, "SMH_3319": {"risk": 0}, "SMH_4579": {"risk": 0}, "SMH_2691": {"risk": 1}, "SMH_2275": {"risk": 0}, "SMH_2543": {"risk": 0}, "SMH_4990": {"risk": 0}, "SMH_743": {"risk": 0}, "SMH_5813": {"risk": 0}, "SMH_6169": {"risk": 0}, "SMH_5093": {"risk": 0}, "SMH_6202": {"risk": 0}, "SMH_3065": {"risk": 0}, "SMH_2508": {"risk": 0}, "SMH_1374": {"risk": 1}, "SMH_2232": {"risk": 0}, "SMH_5781": {"risk": 0}, "SMH_2911": {"risk": 0}, "SMH_4952": {"risk": 0}, "SMH_6005": {"risk": 0}, "SMH_4094": {"risk": 0}, "SMH_3523": {"risk": 1}, "SMH_4055": {"risk": 1}, "SMH_4060": {"risk": 1}, "SMH_905": {"risk": 0}, "SMH_4350": {"risk": 0}, "SMH_3178": {"risk": 0}, "SMH_4173": {"risk": 0}, "SMH_2247": {"risk": 1}, "SMH_5594": {"risk": 1}, "SMH_4503": {"risk": 0}, "SMH_4379": {"risk": 1}, "SMH_3637": {"risk": 0}, "SMH_1162": {"risk": 1}, "SMH_673": {"risk": 0}, "SMH_2322": {"risk": 0}, "SMH_5730": {"risk": 0}, "SMH_941": {"risk": 0}, "SMH_598": {"risk": 0}, "SMH_5570": {"risk": 0}, "SMH_5380": {"risk": 0}, "SMH_2025": {"risk": 1}, "SMH_4547": {"risk": 1}, "SMH_5485": {"risk": 0}, "SMH_3518": {"risk": 1}, "SMH_4207": {"risk": 0}, "SMH_3399": {"risk": 0}, "SMH_5476": {"risk": 0}, "SMH_2639": {"risk": 0}, "SMH_2717": {"risk": 0}, "SMH_5011": {"risk": 1}, "SMH_3867": {"risk": 0}, "SMH_3917": {"risk": 0}, "SMH_4711": {"risk": 1}, "SMH_5308": {"risk": 0}, "SMH_1224": {"risk": 0}, "SMH_2680": {"risk": 0}, "SMH_2581": {"risk": 0}, "SMH_4968": {"risk": 0}, "SMH_3098": {"risk": 0}, "SMH_5521": {"risk": 0}, "SMH_1739": {"risk": 0}, "SMH_3443": {"risk": 0}, "SMH_4556": {"risk": 0}, "SMH_5099": {"risk": 0}, "SMH_3640": {"risk": 0}, "SMH_2479": {"risk": 0}, "SMH_3641": {"risk": 1}, "SMH_5115": {"risk": 0}, "SMH_723": {"risk": 0}, "SMH_2249": {"risk": 0}, "SMH_2736": {"risk": 0}, "SMH_4352": {"risk": 0}, "SMH_5705": {"risk": 0}, "SMH_4589": {"risk": 0}, "SMH_3249": {"risk": 0}, "SMH_5722": {"risk": 0}, "SMH_5545": {"risk": 0}, "SMH_2941": {"risk": 1}, "SMH_5965": {"risk": 0}, "SMH_612": {"risk": 1}, "SMH_1329": {"risk": 0}, "SMH_1853": {"risk": 0}, "SMH_2756": {"risk": 0}, "SMH_1221": {"risk": 0}, "SMH_6079": {"risk": 0}, "SMH_3728": {"risk": 0}, "SMH_1261": {"risk": 1}, "SMH_6065": {"risk": 1}, "SMH_4963": {"risk": 1}, "SMH_5638": {"risk": 0}, "SMH_5016": {"risk": 0}, "SMH_2245": {"risk": 1}, "SMH_1180": {"risk": 0}, "SMH_3312": {"risk": 1}, "SMH_5480": {"risk": 0}, "SMH_3091": {"risk": 0}, "SMH_6022": {"risk": 0}, "SMH_5605": {"risk": 0}, "SMH_1272": {"risk": 1}, "SMH_3703": {"risk": 0}, "SMH_3524": {"risk": 1}, "SMH_3180": {"risk": 0}, "SMH_4976": {"risk": 1}, "SMH_3533": {"risk": 1}, "SMH_4178": {"risk": 0}, "SMH_3544": {"risk": 0}, "SMH_4235": {"risk": 0}, "SMH_5508": {"risk": 0}, "SMH_4541": {"risk": 0}, "SMH_4837": {"risk": 0}, "SMH_2929": {"risk": 0}, "SMH_1072": {"risk": 0}, "SMH_3986": {"risk": 0}, "SMH_2231": {"risk": 0}, "SMH_4785": {"risk": 1}, "SMH_1276": {"risk": 1}, "SMH_5927": {"risk": 1}, "SMH_3552": {"risk": 1}, "SMH_3880": {"risk": 0}, "SMH_3207": {"risk": 0}, "SMH_2826": {"risk": 0}, "SMH_5004": {"risk": 0}, "SMH_683": {"risk": 1}, "SMH_4394": {"risk": 1}, "SMH_4974": {"risk": 0}, "SMH_5344": {"risk": 0}, "SMH_5459": {"risk": 0}, "SMH_3954": {"risk": 0}, "SMH_3695": {"risk": 0}, "SMH_5733": {"risk": 1}, "SMH_1262": {"risk": 0}, "SMH_5014": {"risk": 1}, "SMH_5232": {"risk": 0}, "SMH_4454": {"risk": 0}, "SMH_4808": {"risk": 0}, "SMH_6178": {"risk": 0}, "SMH_563": {"risk": 0}, "SMH_4584": {"risk": 0}, "SMH_5601": {"risk": 1}, "SMH_5513": {"risk": 1}, "SMH_5226": {"risk": 1}, "SMH_3416": {"risk": 0}, "SMH_5842": {"risk": 1}, "SMH_3075": {"risk": 0}, "SMH_4089": {"risk": 0}, "SMH_3335": {"risk": 0}, "SMH_1085": {"risk": 0}, "SMH_5977": {"risk": 1}, "SMH_5542": {"risk": 0}, "SMH_4959": {"risk": 0}, "SMH_5873": {"risk": 0}, "SMH_5488": {"risk": 1}, "SMH_1759": {"risk": 0}, "SMH_4270": {"risk": 0}, "SMH_1936": {"risk": 0}, "SMH_4191": {"risk": 0}, "SMH_3462": {"risk": 0}, "SMH_1044": {"risk": 0}, "SMH_657": {"risk": 0}, "SMH_2220": {"risk": 0}, "SMH_823": {"risk": 0}, "SMH_3386": {"risk": 0}, "SMH_3857": {"risk": 0}, "SMH_6105": {"risk": 1}, "SMH_4468": {"risk": 1}, "SMH_1630": {"risk": 0}, "SMH_1683": {"risk": 0}, "SMH_614": {"risk": 0}, "SMH_715": {"risk": 0}, "SMH_1228": {"risk": 0}, "SMH_5687": {"risk": 1}, "SMH_5502": {"risk": 1}, "SMH_4979": {"risk": 0}, "SMH_592": {"risk": 0}, "SMH_6212": {"risk": 1}, "SMH_1736": {"risk": 0}, "SMH_1439": {"risk": 0}, "SMH_6013": {"risk": 0}, "SMH_601": {"risk": 0}, "SMH_3507": {"risk": 1}, "SMH_5103": {"risk": 1}, "SMH_5203": {"risk": 0}, "SMH_4921": {"risk": 0}, "SMH_5053": {"risk": 0}, "SMH_3112": {"risk": 0}, "SMH_4765": {"risk": 0}, "SMH_3113": {"risk": 0}, "SMH_6226": {"risk": 0}, "SMH_4831": {"risk": 0}, "SMH_2942": {"risk": 1}, "SMH_677": {"risk": 1}, "SMH_4106": {"risk": 1}, "SMH_2065": {"risk": 0}, "SMH_3055": {"risk": 0}, "SMH_3784": {"risk": 0}, "SMH_3886": {"risk": 1}, "SMH_3352": {"risk": 0}, "SMH_5519": {"risk": 0}, "SMH_6164": {"risk": 1}, "SMH_1835": {"risk": 0}, "SMH_3502": {"risk": 0}, "SMH_1777": {"risk": 0}, "SMH_581": {"risk": 0}, "SMH_2493": {"risk": 0}, "SMH_4908": {"risk": 0}, "SMH_684": {"risk": 0}, "SMH_2690": {"risk": 0}, "SMH_2359": {"risk": 0}, "SMH_5534": {"risk": 1}, "SMH_1004": {"risk": 0}, "SMH_5065": {"risk": 1}, "SMH_5177": {"risk": 0}, "SMH_5543": {"risk": 0}, "SMH_2358": {"risk": 0}, "SMH_5694": {"risk": 0}, "SMH_1983": {"risk": 0}, "SMH_6239": {"risk": 0}, "SMH_2925": {"risk": 0}, "SMH_4863": {"risk": 0}, "SMH_1720": {"risk": 0}, "SMH_3521": {"risk": 1}, "SMH_6211": {"risk": 0}, "SMH_5422": {"risk": 1}, "SMH_2058": {"risk": 1}, "SMH_2881": {"risk": 0}, "SMH_3145": {"risk": 0}, "SMH_5354": {"risk": 0}, "SMH_5223": {"risk": 0}, "SMH_2219": {"risk": 0}, "SMH_1271": {"risk": 0}, "SMH_4577": {"risk": 0}, "SMH_625": {"risk": 0}, "SMH_1079": {"risk": 0}, "SMH_5898": {"risk": 0}, "SMH_667": {"risk": 1}, "SMH_3601": {"risk": 0}, "SMH_2093": {"risk": 0}, "SMH_2400": {"risk": 1}, "SMH_3577": {"risk": 0}, "SMH_2503": {"risk": 0}, "SMH_6191": {"risk": 0}, "SMH_3929": {"risk": 0}, "SMH_2679": {"risk": 0}, "SMH_6221": {"risk": 0}, "SMH_6085": {"risk": 0}, "SMH_5526": {"risk": 0}, "SMH_2274": {"risk": 1}, "SMH_1219": {"risk": 0}, "SMH_5492": {"risk": 0}, "SMH_5087": {"risk": 1}, "SMH_4101": {"risk": 0}, "SMH_6157": {"risk": 0}, "SMH_5672": {"risk": 0}, "SMH_1367": {"risk": 0}, "SMH_4953": {"risk": 0}, "SMH_585": {"risk": 1}, "SMH_4946": {"risk": 0}, "SMH_2985": {"risk": 0}, "SMH_2971": {"risk": 0}, "SMH_2903": {"risk": 0}, "SMH_5108": {"risk": 0}, "SMH_725": {"risk": 0}, "SMH_5329": {"risk": 0}, "SMH_2988": {"risk": 0}, "SMH_3576": {"risk": 1}, "SMH_5387": {"risk": 0}, "SMH_2490": {"risk": 0}, "SMH_1958": {"risk": 1}, "SMH_4337": {"risk": 1}, "SMH_4107": {"risk": 0}, "SMH_4458": {"risk": 0}, "SMH_4412": {"risk": 1}, "SMH_5305": {"risk": 0}, "SMH_1037": {"risk": 0}, "SMH_834": {"risk": 0}, "SMH_5575": {"risk": 0}, "SMH_4657": {"risk": 1}, "SMH_4774": {"risk": 0}, "SMH_4636": {"risk": 0}, "SMH_5285": {"risk": 0}, "SMH_4967": {"risk": 0}, "SMH_2873": {"risk": 1}, "SMH_571": {"risk": 1}, "SMH_5742": {"risk": 0}, "SMH_3563": {"risk": 0}, "SMH_3816": {"risk": 0}, "SMH_2148": {"risk": 0}, "SMH_1028": {"risk": 0}, "SMH_800": {"risk": 1}, "SMH_3548": {"risk": 0}, "SMH_3530": {"risk": 0}, "SMH_569": {"risk": 0}, "SMH_4165": {"risk": 1}, "SMH_4180": {"risk": 0}, "SMH_5584": {"risk": 0}, "SMH_2272": {"risk": 0}, "SMH_6127": {"risk": 0}, "SMH_5375": {"risk": 0}, "SMH_1911": {"risk": 1}, "SMH_2936": {"risk": 0}, "SMH_5701": {"risk": 0}, "SMH_5523": {"risk": 0}, "SMH_2299": {"risk": 0}, "SMH_4964": {"risk": 0}, "SMH_2003": {"risk": 0}, "SMH_2473": {"risk": 0}, "SMH_3185": {"risk": 0}, "SMH_5688": {"risk": 0}, "SMH_3470": {"risk": 0}, "SMH_3613": {"risk": 0}, "SMH_3297": {"risk": 0}, "SMH_645": {"risk": 1}, "SMH_3863": {"risk": 0}, "SMH_2727": {"risk": 0}, "SMH_1301": {"risk": 0}, "SMH_5466": {"risk": 0}, "SMH_4821": {"risk": 1}, "SMH_5215": {"risk": 0}, "SMH_6092": {"risk": 0}, "SMH_1216": {"risk": 0}, "SMH_5729": {"risk": 0}, "SMH_5023": {"risk": 0}, "SMH_5811": {"risk": 0}, "SMH_3960": {"risk": 0}, "SMH_613": {"risk": 1}, "SMH_1484": {"risk": 0}, "SMH_4931": {"risk": 0}, "SMH_2809": {"risk": 0}, "SMH_6175": {"risk": 0}, "SMH_583": {"risk": 0}, "SMH_5423": {"risk": 0}, "SMH_5896": {"risk": 0}, "SMH_1500": {"risk": 0}, "SMH_4582": {"risk": 0}, "SMH_4121": {"risk": 0}, "SMH_4489": {"risk": 0}, "SMH_3033": {"risk": 0}, "SMH_6060": {"risk": 0}, "SMH_5995": {"risk": 0}, "SMH_4057": {"risk": 0}, "SMH_5887": {"risk": 1}, "SMH_1847": {"risk": 0}, "SMH_5175": {"risk": 1}, "SMH_594": {"risk": 0}, "SMH_4446": {"risk": 0}, "SMH_4949": {"risk": 0}, "SMH_5258": {"risk": 0}, "SMH_5200": {"risk": 1}, "SMH_6155": {"risk": 0}, "SMH_6107": {"risk": 0}, "SMH_3506": {"risk": 0}, "SMH_5892": {"risk": 1}, "SMH_5903": {"risk": 0}, "SMH_911": {"risk": 0}, "SMH_2919": {"risk": 1}, "SMH_5547": {"risk": 1}, "SMH_4709": {"risk": 0}, "SMH_5509": {"risk": 0}, "SMH_2943": {"risk": 0}, "SMH_4149": {"risk": 0}, "SMH_611": {"risk": 1}, "SMH_1811": {"risk": 0}, "SMH_5364": {"risk": 0}, "SMH_1194": {"risk": 1}, "SMH_1283": {"risk": 0}, "SMH_4878": {"risk": 0}, "SMH_630": {"risk": 1}, "SMH_633": {"risk": 0}, "SMH_2927": {"risk": 0}, "SMH_4287": {"risk": 0}, "SMH_4613": {"risk": 1}, "SMH_5901": {"risk": 0}, "SMH_5517": {"risk": 1}, "SMH_5777": {"risk": 0}, "SMH_3822": {"risk": 1}, "SMH_5174": {"risk": 0}, "SMH_3271": {"risk": 0}, "SMH_5310": {"risk": 1}, "SMH_4267": {"risk": 0}, "SMH_2104": {"risk": 0}, "SMH_5331": {"risk": 0}, "SMH_4012": {"risk": 0}, "SMH_3711": {"risk": 0}, "SMH_6081": {"risk": 0}, "SMH_5810": {"risk": 0}, "SMH_5464": {"risk": 0}, "SMH_4295": {"risk": 0}, "SMH_938": {"risk": 0}, "SMH_1713": {"risk": 0}, "SMH_5843": {"risk": 0}, "SMH_595": {"risk": 0}, "SMH_5684": {"risk": 0}, "SMH_4606": {"risk": 0}, "SMH_6080": {"risk": 0}, "SMH_6114": {"risk": 0}, "SMH_5991": {"risk": 1}, "SMH_3981": {"risk": 1}, "SMH_2681": {"risk": 1}, "SMH_4144": {"risk": 0}, "SMH_4978": {"risk": 0}, "SMH_3555": {"risk": 0}, "SMH_1447": {"risk": 0}, "SMH_582": {"risk": 1}, "SMH_4070": {"risk": 1}, "SMH_5477": {"risk": 1}, "SMH_3497": {"risk": 0}, "SMH_4729": {"risk": 0}, "SMH_2310": {"risk": 0}, "SMH_1227": {"risk": 1}, "SMH_2476": {"risk": 0}, "SMH_4590": {"risk": 0}, "SMH_1066": {"risk": 0}, "SMH_2987": {"risk": 0}, "SMH_4040": {"risk": 0}, "SMH_5902": {"risk": 0}, "SMH_6162": {"risk": 0}, "SMH_3837": {"risk": 1}, "SMH_5550": {"risk": 0}, "SMH_1778": {"risk": 1}, "SMH_3472": {"risk": 0}, "SMH_726": {"risk": 0}, "SMH_2920": {"risk": 0}, "SMH_568": {"risk": 0}, "SMH_2957": {"risk": 0}, "SMH_5447": {"risk": 0}, "SMH_4146": {"risk": 0}, "SMH_1556": {"risk": 0}, "SMH_2877": {"risk": 0}, "SMH_5832": {"risk": 0}, "SMH_5755": {"risk": 0}, "SMH_1576": {"risk": 0}, "SMH_4804": {"risk": 0}, "SMH_1234": {"risk": 0}, "SMH_1555": {"risk": 0}, "SMH_5287": {"risk": 1}, "SMH_5744": {"risk": 0}, "SMH_576": {"risk": 0}, "SMH_6049": {"risk": 0}, "SMH_1048": {"risk": 1}, "SMH_6048": {"risk": 0}, "SMH_1937": {"risk": 0}, "SMH_2020": {"risk": 0}, "SMH_564": {"risk": 0}, "SMH_2293": {"risk": 0}, "SMH_2250": {"risk": 0}, "SMH_5943": {"risk": 0}, "SMH_989": {"risk": 0}, "SMH_5162": {"risk": 0}, "SMH_1851": {"risk": 0}, "SMH_5645": {"risk": 0}, "SMH_5231": {"risk": 0}, "SMH_2018": {"risk": 0}, "SMH_2949": {"risk": 0}, "SMH_2450": {"risk": 0}, "SMH_5290": {"risk": 0}, "SMH_6021": {"risk": 0}, "SMH_5424": {"risk": 0}, "SMH_1342": {"risk": 0}, "SMH_643": {"risk": 0}, "SMH_2437": {"risk": 0}, "SMH_4637": {"risk": 0}, "SMH_4987": {"risk": 1}, "SMH_4277": {"risk": 0}, "SMH_6195": {"risk": 1}, "SMH_4122": {"risk": 0}, "SMH_4084": {"risk": 0}, "SMH_4043": {"risk": 0}, "SMH_6182": {"risk": 0}, "SMH_3591": {"risk": 0}, "SMH_2068": {"risk": 0}, "SMH_2882": {"risk": 0}, "SMH_1837": {"risk": 0}, "SMH_6201": {"risk": 0}, "SMH_1062": {"risk": 1}, "SMH_2089": {"risk": 0}, "SMH_4961": {"risk": 0}, "SMH_4356": {"risk": 0}, "SMH_2474": {"risk": 0}, "SMH_5709": {"risk": 1}, "SMH_2369": {"risk": 0}, "SMH_4655": {"risk": 1}, "SMH_3336": {"risk": 0}, "SMH_728": {"risk": 1}, "SMH_929": {"risk": 0}, "SMH_3975": {"risk": 0}, "SMH_4194": {"risk": 0}, "SMH_4664": {"risk": 1}, "SMH_5128": {"risk": 0}, "SMH_5763": {"risk": 0}, "SMH_3860": {"risk": 0}, "SMH_3923": {"risk": 0}, "SMH_5025": {"risk": 0}, "SMH_2655": {"risk": 0}, "SMH_4713": {"risk": 1}, "SMH_3106": {"risk": 0}, "SMH_3531": {"risk": 1}, "SMH_4014": {"risk": 0}, "SMH_4124": {"risk": 0}, "SMH_1930": {"risk": 0}, "SMH_5678": {"risk": 0}, "SMH_2257": {"risk": 0}, "SMH_2842": {"risk": 0}, "SMH_5316": {"risk": 0}, "SMH_2879": {"risk": 0}, "SMH_4344": {"risk": 0}, "SMH_1114": {"risk": 0}, "SMH_6167": {"risk": 1}, "SMH_6042": {"risk": 0}, "SMH_6028": {"risk": 0}, "SMH_2980": {"risk": 0}, "SMH_644": {"risk": 0}, "SMH_5365": {"risk": 1}, "SMH_2638": {"risk": 0}, "SMH_4984": {"risk": 0}, "SMH_4420": {"risk": 0}, "SMH_6014": {"risk": 1}, "SMH_3512": {"risk": 1}, "SMH_4879": {"risk": 0}, "SMH_6089": {"risk": 0}, "SMH_4871": {"risk": 1}, "SMH_607": {"risk": 1}, "SMH_4177": {"risk": 0}, "SMH_1332": {"risk": 1}, "SMH_5608": {"risk": 0}, "SMH_3485": {"risk": 0}, "SMH_780": {"risk": 1}, "SMH_3008": {"risk": 0}, "SMH_5911": {"risk": 0}, "SMH_5653": {"risk": 0}, "SMH_5456": {"risk": 0}, "SMH_6225": {"risk": 0}, "SMH_893": {"risk": 0}, "SMH_3499": {"risk": 0}, "SMH_4640": {"risk": 0}, "SMH_4140": {"risk": 0}, "SMH_3699": {"risk": 0}, "SMH_5052": {"risk": 1}, "SMH_4947": {"risk": 0}, "SMH_3526": {"risk": 0}, "SMH_5637": {"risk": 0}, "SMH_5041": {"risk": 0}, "SMH_6010": {"risk": 0}, "SMH_4114": {"risk": 0}, "SMH_704": {"risk": 0}, "SMH_5457": {"risk": 0}, "SMH_2874": {"risk": 1}, "SMH_3213": {"risk": 0}, "SMH_1074": {"risk": 1}, "SMH_4174": {"risk": 0}, "SMH_597": {"risk": 0}, "SMH_5105": {"risk": 1}, "SMH_566": {"risk": 1}, "SMH_4079": {"risk": 1}, "SMH_3817": {"risk": 1}, "SMH_596": {"risk": 1}, "SMH_1289": {"risk": 1}, "SMH_5022": {"risk": 0}, "SMH_3438": {"risk": 0}, "SMH_4597": {"risk": 1}, "SMH_573": {"risk": 1}, "SMH_4118": {"risk": 1}, "SMH_5449": {"risk": 0}, "SMH_5920": {"risk": 1}, "SMH_4069": {"risk": 0}, "SMH_2287": {"risk": 0}, "SMH_2090": {"risk": 1}, "SMH_1249": {"risk": 0}, "SMH_620": {"risk": 0}, "SMH_3838": {"risk": 0}, "SMH_1462": {"risk": 0}, "SMH_5394": {"risk": 0}, "SMH_2483": {"risk": 0}, "SMH_2977": {"risk": 0}, "SMH_3069": {"risk": 1}, "SMH_5385": {"risk": 1}, "SMH_4050": {"risk": 0}, "SMH_5311": {"risk": 0}, "SMH_5838": {"risk": 0}, "SMH_894": {"risk": 0}, "SMH_5493": {"risk": 0}, "SMH_3585": {"risk": 0}, "SMH_4576": {"risk": 0}, "SMH_1294": {"risk": 0}, "SMH_4882": {"risk": 0}, "SMH_4719": {"risk": 0}, "SMH_1225": {"risk": 0}, "SMH_3135": {"risk": 0}, "SMH_3553": {"risk": 1}, "SMH_654": {"risk": 0}, "SMH_4561": {"risk": 0}, "SMH_5889": {"risk": 0}, "SMH_1086": {"risk": 0}, "SMH_4759": {"risk": 0}, "SMH_2896": {"risk": 0}, "SMH_5313": {"risk": 0}, "SMH_626": {"risk": 1}, "SMH_1961": {"risk": 0}, "SMH_3394": {"risk": 0}, "SMH_682": {"risk": 0}, "SMH_3378": {"risk": 0}, "SMH_1718": {"risk": 0}, "SMH_1293": {"risk": 1}, "SMH_1968": {"risk": 1}, "SMH_3906": {"risk": 1}, "SMH_1877": {"risk": 0}, "SMH_2565": {"risk": 1}, "SMH_4046": {"risk": 1}, "SMH_1189": {"risk": 0}, "SMH_4972": {"risk": 1}, "SMH_5554": {"risk": 0}, "SMH_4680": {"risk": 0}, "SMH_4998": {"risk": 0}, "SMH_5899": {"risk": 1}, "SMH_1259": {"risk": 0}, "SMH_2367": {"risk": 0}, "SMH_4973": {"risk": 1}, "SMH_5013": {"risk": 0}, "SMH_5566": {"risk": 1}, "SMH_2600": {"risk": 1}, "SMH_4017": {"risk": 1}, "SMH_6194": {"risk": 0}, "SMH_1358": {"risk": 0}, "SMH_4166": {"risk": 1}, "SMH_2404": {"risk": 0}, "SMH_5475": {"risk": 0}, "SMH_2692": {"risk": 0}, "SMH_1421": {"risk": 1}, "SMH_4119": {"risk": 0}, "SMH_2248": {"risk": 1}, "SMH_1620": {"risk": 1}, "SMH_5032": {"risk": 0}, "SMH_6043": {"risk": 0}, "SMH_1613": {"risk": 0}, "SMH_2843": {"risk": 0}, "SMH_5345": {"risk": 0}, "SMH_4773": {"risk": 1}, "SMH_2912": {"risk": 1}, "SMH_946": {"risk": 0}, "SMH_1052": {"risk": 0}, "SMH_5764": {"risk": 0}, "SMH_5500": {"risk": 0}, "SMH_3080": {"risk": 0}, "SMH_5208": {"risk": 0}, "SMH_5712": {"risk": 0}, "SMH_3517": {"risk": 1}, "SMH_4604": {"risk": 0}, "SMH_1913": {"risk": 0}, "SMH_562": {"risk": 0}, "SMH_1376": {"risk": 0}, "SMH_4102": {"risk": 0}, "SMH_5507": {"risk": 1}, "SMH_2887": {"risk": 0}, "SMH_2273": {"risk": 1}, "SMH_4651": {"risk": 0}, "SMH_3800": {"risk": 0}, "SMH_3402": {"risk": 0}, "SMH_4078": {"risk": 1}, "SMH_5473": {"risk": 0}, "SMH_6071": {"risk": 0}, "SMH_5685": {"risk": 0}, "SMH_3864": {"risk": 0}, "SMH_4453": {"risk": 0}, "SMH_5326": {"risk": 0}, "SMH_577": {"risk": 0}, "SMH_5470": {"risk": 0}, "SMH_3570": {"risk": 0}, "SMH_5038": {"risk": 0}, "SMH_4167": {"risk": 0}, "SMH_5724": {"risk": 0}, "SMH_5318": {"risk": 1}, "SMH_1269": {"risk": 1}, "SMH_636": {"risk": 0}, "SMH_5998": {"risk": 0}, "SMH_4643": {"risk": 1}, "SMH_5286": {"risk": 1}, "SMH_5647": {"risk": 1}, "SMH_1715": {"risk": 0}, "SMH_6218": {"risk": 1}, "SMH_3793": {"risk": 0}, "SMH_5270": {"risk": 1}, "SMH_4943": {"risk": 1}, "SMH_1935": {"risk": 0}, "SMH_1744": {"risk": 1}, "SMH_807": {"risk": 0}, "SMH_1866": {"risk": 0}, "SMH_5824": {"risk": 0}, "SMH_2001": {"risk": 0}, "SMH_6100": {"risk": 0}, "SMH_4588": {"risk": 0}, "SMH_4569": {"risk": 0}, "SMH_5540": {"risk": 1}, "SMH_3079": {"risk": 0}, "SMH_5816": {"risk": 0}, "SMH_2261": {"risk": 1}, "SMH_2858": {"risk": 0}, "SMH_5471": {"risk": 1}, "SMH_3928": {"risk": 0}, "SMH_5239": {"risk": 1}, "SMH_5075": {"risk": 1}, "SMH_615": {"risk": 0}, "SMH_5932": {"risk": 0}, "SMH_4580": {"risk": 0}, "SMH_5983": {"risk": 0}, "SMH_2924": {"risk": 0}, "SMH_2860": {"risk": 0}, "SMH_4138": {"risk": 0}, "SMH_2631": {"risk": 0}, "SMH_5921": {"risk": 0}, "SMH_6158": {"risk": 0}, "SMH_3090": {"risk": 0}, "SMH_5966": {"risk": 1}, "SMH_5448": {"risk": 1}, "SMH_3803": {"risk": 0}, "SMH_2103": {"risk": 0}, "SMH_4097": {"risk": 0}, "SMH_2821": {"risk": 0}, "SMH_801": {"risk": 1}, "SMH_2672": {"risk": 1}, "SMH_3810": {"risk": 0}, "SMH_4805": {"risk": 1}, "SMH_2514": {"risk": 1}, "SMH_1343": {"risk": 0}, "SMH_637": {"risk": 1}, "SMH_599": {"risk": 1}, "SMH_580": {"risk": 1}, "SMH_1860": {"risk": 0}, "SMH_2254": {"risk": 0}, "SMH_6045": {"risk": 1}, "SMH_2394": {"risk": 1}, "SMH_1963": {"risk": 0}, "SMH_5904": {"risk": 0}, "SMH_5851": {"risk": 1}, "SMH_6179": {"risk": 0}, "SMH_6093": {"risk": 1}, "SMH_4726": {"risk": 0}, "SMH_4427": {"risk": 0}, "SMH_5616": {"risk": 0}, "SMH_4969": {"risk": 0}, "SMH_575": {"risk": 1}, "SMH_6090": {"risk": 1}, "SMH_4214": {"risk": 0}, "SMH_4062": {"risk": 0}, "SMH_6004": {"risk": 0}, "SMH_3845": {"risk": 0}, "SMH_3891": {"risk": 0}, "SMH_6098": {"risk": 0}, "SMH_561": {"risk": 1}, "SMH_4591": {"risk": 0}, "SMH_5454": {"risk": 0}, "SMH_5469": {"risk": 0}, "SMH_731": {"risk": 0}, "SMH_5176": {"risk": 1}, "SMH_4110": {"risk": 1}, "SMH_1239": {"risk": 1}, "SMH_3534": {"risk": 0}, "SMH_5453": {"risk": 1}, "SMH_2962": {"risk": 1}, "SMH_2939": {"risk": 0}, "SMH_4340": {"risk": 0}, "SMH_638": {"risk": 0}, "SMH_586": {"risk": 1}, "SMH_1597": {"risk": 0}, "SMH_2946": {"risk": 0}, "SMH_5348": {"risk": 0}, "SMH_4623": {"risk": 1}, "SMH_5035": {"risk": 0}, "SMH_3105": {"risk": 1}, "SMH_3398": {"risk": 1}, "SMH_3545": {"risk": 1}, "SMH_5061": {"risk": 0}, "SMH_703": {"risk": 0}, "SMH_1196": {"risk": 0}, "SMH_2854": {"risk": 0}, "SMH_5401": {"risk": 0}, "SMH_6072": {"risk": 0}, "SMH_4723": {"risk": 1}, "SMH_5494": {"risk": 0}, "SMH_5510": {"risk": 0}, "SMH_878": {"risk": 0}, "SMH_757": {"risk": 0}, "SMH_574": {"risk": 1}, "SMH_1123": {"risk": 0}, "SMH_3479": {"risk": 1}, "SMH_5481": {"risk": 1}, "SMH_2362": {"risk": 0}, "SMH_2570": {"risk": 0}, "SMH_5234": {"risk": 0}, "SMH_1730": {"risk": 0}, "SMH_4603": {"risk": 0}, "SMH_5088": {"risk": 0}, "SMH_2678": {"risk": 0}, "SMH_4994": {"risk": 0}, "SMH_4832": {"risk": 1}, "SMH_2492": {"risk": 0}, "SMH_1689": {"risk": 0}, "SMH_2083": {"risk": 0}, "SMH_2294": {"risk": 0}, "SMH_3500": {"risk": 0}, "SMH_2986": {"risk": 0}, "SMH_3922": {"risk": 0}, "SMH_4103": {"risk": 0}, "SMH_1623": {"risk": 1}, "SMH_3535": {"risk": 1}, "SMH_5555": {"risk": 1}, "SMH_3408": {"risk": 1}, "SMH_6190": {"risk": 0}, "SMH_4641": {"risk": 0}, "SMH_5257": {"risk": 0}, "SMH_2192": {"risk": 0}, "SMH_835": {"risk": 1}, "SMH_2876": {"risk": 0}, "SMH_972": {"risk": 0}, "SMH_4846": {"risk": 0}, "SMH_4188": {"risk": 0}, "SMH_4385": {"risk": 0}, "SMH_1188": {"risk": 1}, "SMH_5018": {"risk": 0}, "SMH_4032": {"risk": 0}, "SMH_3390": {"risk": 0}, "SMH_4268": {"risk": 1}, "SMH_1031": {"risk": 0}, "SMH_1360": {"risk": 0}, "SMH_3243": {"risk": 0}, "SMH_6199": {"risk": 1}, "SMH_4681": {"risk": 0}, "SMH_1223": {"risk": 1}, "SMH_5007": {"risk": 0}, "SMH_6062": {"risk": 0}, "SMH_6216": {"risk": 1}, "SMH_2751": {"risk": 0}, "SMH_590": {"risk": 1}, "SMH_5237": {"risk": 1}, "SMH_5822": {"risk": 1}, "SMH_5942": {"risk": 0}, "SMH_5443": {"risk": 1}, "SMH_5118": {"risk": 0}, "SMH_5019": {"risk": 0}, "SMH_5530": {"risk": 0}, "SMH_2571": {"risk": 1}, "SMH_3344": {"risk": 0}, "SMH_3673": {"risk": 0}, "SMH_5522": {"risk": 0}, "SMH_603": {"risk": 0}, "SMH_4514": {"risk": 0}, "SMH_565": {"risk": 1}, "SMH_4686": {"risk": 1}, "SMH_5070": {"risk": 1}, "SMH_2554": {"risk": 0}, "SMH_5894": {"risk": 0}, "SMH_2230": {"risk": 0}, "SMH_3682": {"risk": 1}, "SMH_5915": {"risk": 1}, "SMH_1134": {"risk": 0}, "SMH_5496": {"risk": 0}, "SMH_5881": {"risk": 0}, "SMH_706": {"risk": 0}, "SMH_5725": {"risk": 1}, "SMH_4231": {"risk": 0}, "SMH_5629": {"risk": 0}, "SMH_4535": {"risk": 0}, "SMH_5533": {"risk": 1}, "SMH_1453": {"risk": 1}, "SMH_5396": {"risk": 0}, "SMH_5049": {"risk": 0}, "SMH_5668": {"risk": 0}, "SMH_2266": {"risk": 1}, "SMH_5461": {"risk": 1}, "SMH_4910": {"risk": 0}, "SMH_2280": {"risk": 0}, "SMH_3651": {"risk": 0}, "SMH_3514": {"risk": 1}, "SMH_6059": {"risk": 0}, "SMH_3807": {"risk": 0}, "SMH_1043": {"risk": 0}, "SMH_4995": {"risk": 0}, "SMH_3694": {"risk": 1}, "SMH_1095": {"risk": 1}, "SMH_4740": {"risk": 0}, "SMH_2720": {"risk": 0}, "SMH_4150": {"risk": 1}, "SMH_3593": {"risk": 1}, "SMH_5068": {"risk": 0}, "SMH_5390": {"risk": 0}, "SMH_5067": {"risk": 0}, "SMH_1304": {"risk": 1}, "SMH_1685": {"risk": 0}, "SMH_5914": {"risk": 0}, "SMH_1747": {"risk": 1}, "SMH_557": {"risk": 1}, "SMH_3357": {"risk": 0}, "SMH_3293": {"risk": 1}, "SMH_5297": {"risk": 0}, "SMH_5427": {"risk": 0}, "SMH_3151": {"risk": 0}, "SMH_3549": {"risk": 1}, "SMH_2823": {"risk": 1}, "SMH_4542": {"risk": 0}, "SMH_4764": {"risk": 0}, "SMH_1307": {"risk": 0}, "SMH_3889": {"risk": 0}, "SMH_3743": {"risk": 0}, "SMH_1268": {"risk": 0}, "SMH_5002": {"risk": 0}, "SMH_2883": {"risk": 0}, "SMH_3866": {"risk": 0}, "SMH_2237": {"risk": 0}, "SMH_1951": {"risk": 0}, "SMH_5960": {"risk": 1}, "SMH_1959": {"risk": 1}, "SMH_2251": {"risk": 0}, "SMH_567": {"risk": 0}, "SMH_5063": {"risk": 0}, "SMH_559": {"risk": 0}, "SMH_4600": {"risk": 0}, "SMH_3308": {"risk": 0}, "SMH_4684": {"risk": 1}, "SMH_5607": {"risk": 0}, "SMH_5465": {"risk": 1}, "SMH_6091": {"risk": 0}, "SMH_5403": {"risk": 0}, "SMH_6095": {"risk": 0}, "SMH_3400": {"risk": 1}, "SMH_5003": {"risk": 0}, "SMH_5963": {"risk": 0}, "SMH_4260": {"risk": 1}, "SMH_2909": {"risk": 1}, "SMH_3509": {"risk": 0}, "SMH_2012": {"risk": 0}, "SMH_1270": {"risk": 1}, "SMH_1333": {"risk": 1}, "SMH_2888": {"risk": 0}, "SMH_5971": {"risk": 0}, "SMH_1053": {"risk": 0}, "SMH_4051": {"risk": 0}, "SMH_3481": {"risk": 0}, "SMH_3215": {"risk": 0}, "SMH_5693": {"risk": 0}, "SMH_4384": {"risk": 0}, "SMH_5491": {"risk": 0}, "SMH_2092": {"risk": 0}, "SMH_2365": {"risk": 0}, "SMH_1146": {"risk": 0}, "SMH_6073": {"risk": 1}, "SMH_5531": {"risk": 0}, "SMH_4981": {"risk": 1}, "SMH_5073": {"risk": 0}, "SMH_5770": {"risk": 0}, "SMH_4211": {"risk": 0}, "SMH_4977": {"risk": 1}, "SMH_2907": {"risk": 1}, "SMH_2892": {"risk": 0}, "SMH_5012": {"risk": 1}, "SMH_5558": {"risk": 1}, "SMH_1024": {"risk": 0}, "SMH_988": {"risk": 0}, "SMH_5188": {"risk": 0}, "SMH_830": {"risk": 0}, "SMH_5506": {"risk": 1}, "SMH_5756": {"risk": 0}, "SMH_2996": {"risk": 0}, "SMH_2834": {"risk": 0}, "SMH_3233": {"risk": 0}, "SMH_5031": {"risk": 1}, "SMH_3342": {"risk": 0}, "SMH_4951": {"risk": 1}, "SMH_4083": {"risk": 1}, "SMH_658": {"risk": 0}, "SMH_3871": {"risk": 0}, "SMH_1598": {"risk": 1}, "SMH_6156": {"risk": 1}, "SMH_593": {"risk": 0}, "SMH_4618": {"risk": 1}, "SMH_5009": {"risk": 1}, "SMH_3107": {"risk": 0}, "SMH_3117": {"risk": 0}, "SMH_3944": {"risk": 1}, "SMH_5036": {"risk": 0}, "SMH_2451": {"risk": 1}, "SMH_610": {"risk": 0}, "SMH_6173": {"risk": 1}, "SMH_570": {"risk": 0}, "SMH_4982": {"risk": 0}, "SMH_5102": {"risk": 1}, "SMH_2094": {"risk": 0}, "SMH_1212": {"risk": 0}, "SMH_3546": {"risk": 0}, "SMH_5047": {"risk": 0}, "SMH_759": {"risk": 1}, "SMH_6172": {"risk": 0}, "SMH_5765": {"risk": 0}, "SMH_2900": {"risk": 1}, "SMH_655": {"risk": 0}, "SMH_5602": {"risk": 1}, "SMH_3496": {"risk": 1}, "SMH_2585": {"risk": 0}, "SMH_2976": {"risk": 1}, "SMH_3560": {"risk": 0}, "SMH_2935": {"risk": 0}, "SMH_5520": {"risk": 0}, "SMH_826": {"risk": 0}, "SMH_3582": {"risk": 0}, "SMH_4136": {"risk": 1}, "SMH_3280": {"risk": 1}, "SMH_875": {"risk": 0}, "SMH_5590": {"risk": 1}, "SMH_5097": {"risk": 0}, "SMH_6151": {"risk": 0}, "SMH_4262": {"risk": 0}, "SMH_4048": {"risk": 0}, "SMH_4956": {"risk": 0}, "SMH_4349": {"risk": 0}, "SMH_616": {"risk": 0}, "SMH_5304": {"risk": 0}, "SMH_1253": {"risk": 0}, "SMH_681": {"risk": 0}, "SMH_4743": {"risk": 0}, "SMH_794": {"risk": 0}, "SMH_5740": {"risk": 0}, "SMH_5829": {"risk": 0}, "SMH_5858": {"risk": 0}, "SMH_2360": {"risk": 0}, "SMH_6168": {"risk": 0}, "SMH_5064": {"risk": 0}, "SMH_4533": {"risk": 0}, "SMH_4925": {"risk": 0}, "SMH_2841": {"risk": 0}, "SMH_809": {"risk": 0}, "SMH_641": {"risk": 0}, "SMH_4550": {"risk": 1}, "SMH_3260": {"risk": 1}, "SMH_3625": {"risk": 1}, "SMH_5219": {"risk": 0}, "SMH_928": {"risk": 0}, "SMH_1041": {"risk": 0}, "SMH_1349": {"risk": 0}, "SMH_2982": {"risk": 0}, "SMH_2417": {"risk": 0}, "SMH_3561": {"risk": 1}, "SMH_4585": {"risk": 0}, "SMH_5472": {"risk": 0}, "SMH_4890": {"risk": 0}, "SMH_4626": {"risk": 0}, "SMH_3962": {"risk": 0}, "SMH_4232": {"risk": 0}, "SMH_3778": {"risk": 0}, "SMH_5834": {"risk": 0}, "SMH_6203": {"risk": 0}, "SMH_2905": {"risk": 1}, "SMH_5046": {"risk": 0}, "SMH_1036": {"risk": 0}, "SMH_2495": {"risk": 0}, "SMH_5079": {"risk": 0}, "SMH_2630": {"risk": 0}, "SMH_5854": {"risk": 0}, "SMH_6103": {"risk": 0}, "SMH_5888": {"risk": 0}, "SMH_1361": {"risk": 0}, "SMH_1213": {"risk": 1}, "SMH_5757": {"risk": 0}, "SMH_1279": {"risk": 0}, "SMH_1312": {"risk": 0}, "SMH_5214": {"risk": 0}, "SMH_659": {"risk": 0}, "SMH_5895": {"risk": 1}, "SMH_1681": {"risk": 1}, "SMH_5527": {"risk": 0}, "SMH_1274": {"risk": 0}, "SMH_5579": {"risk": 0}, "SMH_6006": {"risk": 1}, "SMH_5803": {"risk": 0}, "SMH_714": {"risk": 0}, "SMH_4970": {"risk": 0}, "SMH_5793": {"risk": 0}, "SMH_3953": {"risk": 0}, "SMH_4622": {"risk": 1}, "SMH_5495": {"risk": 1}, "SMH_5486": {"risk": 1}, "SMH_901": {"risk": 0}, "SMH_2226": {"risk": 0}, "SMH_4609": {"risk": 1}, "SMH_4598": {"risk": 0}, "SMH_4966": {"risk": 1}, "SMH_2286": {"risk": 0}, "SMH_2926": {"risk": 0}, "SMH_6137": {"risk": 0}, "SMH_4942": {"risk": 0}, "SMH_4983": {"risk": 0}, "SMH_2284": {"risk": 0}, "SMH_4370": {"risk": 1}, "SMH_5325": {"risk": 0}, "SMH_6130": {"risk": 0}, "SMH_4971": {"risk": 0}, "SMH_5808": {"risk": 1}, "SMH_6000": {"risk": 0}, "SMH_4068": {"risk": 0}, "SMH_628": {"risk": 0}, "SMH_5340": {"risk": 0}, "SMH_2356": {"risk": 1}, "SMH_2263": {"risk": 1}, "SMH_4164": {"risk": 0}, "SMH_1522": {"risk": 0}, "SMH_2626": {"risk": 1}, "SMH_1320": {"risk": 0}, "SMH_3584": {"risk": 0}, "SMH_1156": {"risk": 1}, "SMH_4380": {"risk": 0}, "SMH_6126": {"risk": 1}, "SMH_2264": {"risk": 0}, "SMH_3942": {"risk": 0}, "SMH_6136": {"risk": 0}, "SMH_2931": {"risk": 0}, "SMH_3692": {"risk": 0}, "SMH_4322": {"risk": 1}, "SMH_5430": {"risk": 0}, "SMH_3538": {"risk": 0}, "SMH_5702": {"risk": 0}, "SMH_2983": {"risk": 1}, "SMH_3604": {"risk": 0}, "SMH_5845": {"risk": 0}, "SMH_631": {"risk": 0}, "SMH_4139": {"risk": 0}, "SMH_2590": {"risk": 0}, "SMH_6011": {"risk": 0}, "SMH_4581": {"risk": 0}, "SMH_6053": {"risk": 0}, "SMH_2053": {"risk": 0}, "SMH_2923": {"risk": 0}, "SMH_4602": {"risk": 1}, "SMH_4980": {"risk": 1}, "SMH_2290": {"risk": 0}, "SMH_2534": {"risk": 0}, "SMH_3569": {"risk": 0}, "SMH_5837": {"risk": 0}, "SMH_1344": {"risk": 0}, "SMH_4154": {"risk": 0}, "SMH_5029": {"risk": 0}, "SMH_4683": {"risk": 1}, "SMH_1533": {"risk": 0}, "SMH_3887": {"risk": 0}, "SMH_6044": {"risk": 0}, "SMH_4555": {"risk": 0}, "SMH_5419": {"risk": 0}, "SMH_4997": {"risk": 0}, "SMH_4750": {"risk": 0}, "SMH_762": {"risk": 1}, "SMH_4047": {"risk": 0}, "SMH_4960": {"risk": 0}, "SMH_6018": {"risk": 0}, "SMH_5700": {"risk": 0}, "SMH_5452": {"risk": 0}, "SMH_1148": {"risk": 0}, "SMH_5439": {"risk": 0}, "SMH_2792": {"risk": 1}, "SMH_5256": {"risk": 0}, "SMH_6144": {"risk": 0}, "SMH_2530": {"risk": 0}, "SMH_5376": {"risk": 0}, "SMH_4066": {"risk": 1}, "SMH_2259": {"risk": 1}, "SMH_2839": {"risk": 0}, "SMH_2342": {"risk": 0}, "SMH_913": {"risk": 0}, "SMH_5392": {"risk": 0}, "SMH_5006": {"risk": 0}, "SMH_6047": {"risk": 0}, "SMH_5868": {"risk": 0}, "SMH_984": {"risk": 0}, "SMH_3971": {"risk": 1}, "SMH_4440": {"risk": 0}, "SMH_4049": {"risk": 0}, "SMH_2650": {"risk": 0}, "SMH_2346": {"risk": 0}, "SMH_3571": {"risk": 1}, "SMH_600": {"risk": 1}, "SMH_5856": {"risk": 0}, "SMH_5751": {"risk": 1}, "SMH_2984": {"risk": 0}, "SMH_2628": {"risk": 0}, "SMH_3536": {"risk": 1}, "SMH_5890": {"risk": 0}, "SMH_5812": {"risk": 0}, "SMH_5458": {"risk": 0}, "SMH_3566": {"risk": 0}, "SMH_2872": {"risk": 1}, "SMH_4620": {"risk": 1}, "SMH_1948": {"risk": 1}, "SMH_4596": {"risk": 0}, "SMH_2227": {"risk": 0}, "SMH_5474": {"risk": 0}, "SMH_2307": {"risk": 1}, "SMH_2353": {"risk": 0}, "SMH_5828": {"risk": 0}, "SMH_1106": {"risk": 0}, "SMH_6227": {"risk": 0}, "SMH_3374": {"risk": 0}, "SMH_3310": {"risk": 1}, "SMH_3769": {"risk": 1}, "SMH_3525": {"risk": 0}, "SMH_2276": {"risk": 0}, "SMH_2945": {"risk": 1}, "SMH_4041": {"risk": 0}, "SMH_2195": {"risk": 0}, "SMH_1295": {"risk": 0}, "SMH_5455": {"risk": 0}, "SMH_4595": {"risk": 0}, "SMH_2271": {"risk": 0}, "SMH_4739": {"risk": 0}, "SMH_3076": {"risk": 1}, "SMH_1638": {"risk": 0}, "SMH_2693": {"risk": 0}, "SMH_1231": {"risk": 0}, "SMH_2895": {"risk": 1}, "SMH_3022": {"risk": 0}, "SMH_4944": {"risk": 0}, "SMH_6152": {"risk": 0}, "SMH_3122": {"risk": 0}, "SMH_4945": {"risk": 0}, "SMH_5850": {"risk": 0}, "SMH_2233": {"risk": 1}, "SMH_5246": {"risk": 1}, "SMH_5731": {"risk": 0}, "SMH_5836": {"risk": 0}, "SMH_5487": {"risk": 0}, "SMH_772": {"risk": 0}, "SMH_5900": {"risk": 0}, "SMH_3843": {"risk": 1}, "SMH_1912": {"risk": 0}, "SMH_2235": {"risk": 1}, "SMH_5107": {"risk": 0}, "SMH_622": {"risk": 1}, "SMH_889": {"risk": 1}, "SMH_4302": {"risk": 1}, "SMH_3361": {"risk": 0}, "SMH_871": {"risk": 1}, "SMH_3516": {"risk": 0}, "SMH_602": {"risk": 0}, "SMH_2897": {"risk": 1}, "SMH_6219": {"risk": 0}, "SMH_6026": {"risk": 0}, "SMH_2229": {"risk": 1}, "SMH_4592": {"risk": 1}, "SMH_4501": {"risk": 0}, "SMH_4599": {"risk": 0}, "SMH_3510": {"risk": 0}, "SMH_4853": {"risk": 0}, "SMH_4950": {"risk": 0}, "SMH_3120": {"risk": 1}, "SMH_3721": {"risk": 0}, "SMH_6033": {"risk": 0}, "SMH_5342": {"risk": 0}, "SMH_4834": {"risk": 0}, "SMH_4067": {"risk": 0}, "SMH_3693": {"risk": 0}, "SMH_4010": {"risk": 0}, "SMH_746": {"risk": 0}, "SMH_2246": {"risk": 0}, "SMH_4958": {"risk": 0}, "SMH_975": {"risk": 0}, "SMH_4583": {"risk": 1}, "SMH_5950": {"risk": 0}, "SMH_6222": {"risk": 0}, "SMH_754": {"risk": 1}, "SMH_1235": {"risk": 0}, "SMH_3957": {"risk": 1}, "SMH_4868": {"risk": 0}, "SMH_3851": {"risk": 0}, "SMH_2978": {"risk": 1}}